gitlab_manager/__init__.py
gitlab_manager/gitlab_api.py
gitlab_manager/main.py
gitlab_manager/utils.py
gitlab_manager-0.17.dist-info/METADATA
gitlab_manager-0.17.dist-info/WHEEL
gitlab_manager-0.17.dist-info/entry_points.txt
gitlab_manager-0.17.dist-info/top_level.txt
gitlab_manager-0.17.dist-info/RECORD
