Metadata-Version: 2.1
Name: gitlab-manager
Version: 0.17
Requires-Dist: python-dotenv
Requires-Dist: requests
Requires-Dist: python-gitlab
